MANIFEST.in
README.rst
setup.cfg
setup.py
ines/__init__.py
ines/authentication.py
ines/authorization.py
ines/cache.py
ines/cleaner.py
ines/config.py
ines/cron.py
ines/exceptions.py
ines/i18n.py
ines/interfaces.py
ines/locks.py
ines/mimetype.py
ines/path.py
ines/renderers.py
ines/request.py
ines/route.py
ines/system.py
ines/utils.py
ines/view.py
ines/wsgi.py
ines.egg-info/PKG-INFO
ines.egg-info/SOURCES.txt
ines.egg-info/dependency_links.txt
ines.egg-info/entry_points.txt
ines.egg-info/not-zip-safe
ines.egg-info/requires.txt
ines.egg-info/top_level.txt
ines/api/__init__.py
ines/api/jobs.py
ines/api/logs.py
ines/api/mailer.py
ines/api/policy.py
ines/api/storage.py
ines/api/core/__init__.py
ines/api/core/database.py
ines/api/core/views.py
ines/api/database/__init__.py
ines/api/database/sql.py
ines/convert/__init__.py
ines/convert/codes.py
ines/convert/dates.py
ines/convert/metrics.py
ines/convert/strings.py
ines/locale/ines.pot
ines/locale/pt/LC_MESSAGES/ines.mo
ines/locale/pt/LC_MESSAGES/ines.po
ines/locale/pt/LC_MESSAGES/ines.po~
ines/middlewares/__init__.py
ines/middlewares/cors.py
ines/middlewares/logs.py
ines/middlewares/payload.py
ines/middlewares/repozetm.py
ines/scripts/__init__.py
ines/scripts/apidocjs.py
ines/views/__init__.py
ines/views/fields.py
ines/views/input.py
ines/views/output.py
ines/views/postman.py
ines/views/schema.py