Metadata-Version: 1.1
Name: ines
Version: 0.1a2
Summary: Web applications manager for pyramid packages
Home-page: https://github.com/hugobranq/ines
Author: Hugo Branquinho
Author-email: hugobranq@gmail.com
License: MIT license
Download-URL: https://github.com/hugobranq/ines/tarball/0.1
Keywords: web wsgi pylons pyramid utilities core
Platform: UNKNOWN
Classifier: Development Status :: 3 - Alpha
Classifier: Intended Audience :: Developers
Classifier: Natural Language :: English
Classifier: Framework :: Pyramid
Classifier: Operating System :: MacOS :: MacOS X
Classifier: Operating System :: Unix
Classifier: Programming Language :: Python :: 2.6
Classifier: Programming Language :: Python :: 2.7
Classifier: License :: OSI Approved :: MIT License
Classifier: Topic :: Internet :: WWW/HTTP
Classifier: Topic :: Internet :: WWW/HTTP :: WSGI
Classifier: Topic :: Utilities
